Workbook

Sheet Case 2 - Amortization
A1: period t | B1: date | C1: begin. book value | D1: coupon | E1: interest exp. | F1: disc. amort. | G1: end. book val.
A2: 0 | B2: 46249 | G2: 83.7401
A3: 1 | B3: 46433 | C3: =G2 -> 83.7401 | D3: =100*0.065/2 -> 3.25 | E3: =C3*(0.09/2) -> 3.7683045 | F3: =E3-D3 -> 0.5183045 | G3: =C3+F3 -> 84.258404
A4: 2 | B4: 46614 | C4: =G3 -> 84.258404 | D4: =100*0.065/2 -> 3.25 | E4: =C4*(0.09/2) -> 3.7916282 | F4: =E4-D4 -> 0.5416282 | G4: =C4+F4 -> 84.800033
A5: 3 | B5: 46798 | C5: =G4 -> 84.800033 | D5: =100*0.065/2 -> 3.25 | E5: =C5*(0.09/2) -> 3.8160015 | F5: =E5-D5 -> 0.56600147 | G5: =C5+F5 -> 85.366034
A6: 4 | B6: 46980 | C6: =G5 -> 85.366034 | D6: =100*0.065/2 -> 3.25 | E6: =C6*(0.09/2) -> 3.8414715 | F6: =E6-D6 -> 0.59147154 | G6: =C6+F6 -> 85.957506
A7: 5 | B7: 47164 | C7: =G6 -> 85.957506 | D7: =100*0.065/2 -> 3.25 | E7: =C7*(0.09/2) -> 3.8680878 | F7: =E7-D7 -> 0.61808776 | G7: =C7+F7 -> 86.575593
A8: 6 | B8: 47345 | C8: =G7 -> 86.575593 | D8: =100*0.065/2 -> 3.25 | E8: =C8*(0.09/2) -> 3.8959017 | F8: =E8-D8 -> 0.64590171 | G8: =C8+F8 -> 87.221495
A9: 7 | B9: 47529 | C9: =G8 -> 87.221495 | D9: =100*0.065/2 -> 3.25 | E9: =C9*(0.09/2) -> 3.9249673 | F9: =E9-D9 -> 0.67496728 | G9: =C9+F9 -> 87.896462
A10: 8 | B10: 47710 | C10: =G9 -> 87.896462 | D10: =100*0.065/2 -> 3.25 | E10: =C10*(0.09/2) -> 3.9553408 | F10: =E10-D10 -> 0.70534081 | G10: =C10+F10 -> 88.601803
A11: 9 | B11: 47894 | C11: =G10 -> 88.601803 | D11: =100*0.065/2 -> 3.25 | E11: =C11*(0.09/2) -> 3.9870811 | F11: =E11-D11 -> 0.73708115 | G11: =C11+F11 -> 89.338884
A12: 10 | B12: 48075 | C12: =G11 -> 89.338884 | D12: =100*0.065/2 -> 3.25 | E12: =C12*(0.09/2) -> 4.0202498 | F12: =E12-D12 -> 0.7702498 | G12: =C12+F12 -> 90.109134
A13: 11 | B13: 48259 | C13: =G12 -> 90.109134 | D13: =100*0.065/2 -> 3.25 | E13: =C13*(0.09/2) -> 4.054911 | F13: =E13-D13 -> 0.80491104 | G13: =C13+F13 -> 90.914045
A14: 12 | B14: 48441 | C14: =G13 -> 90.914045 | D14: =100*0.065/2 -> 3.25 | E14: =C14*(0.09/2) -> 4.091132 | F14: =E14-D14 -> 0.84113204 | G14: =C14+F14 -> 91.755177
... A22: 20 | B22: 49902 | C22: =G21 -> 98.803875 | D22: =100*0.065/2 -> 3.25 | E22: =C22*(0.09/2) -> 4.4461744 | F22: =E22-D22 -> 1.1961744 | G22: =C22+F22 -> 100.00005

Sheet Case 3 - Z Spread
A1: Goal Seek -> | B1: r= | C1: 0.035297026 | D1: s= | E1: 0.011289769
A3: k | B3: CF_k | C3: PV_k | D3: z_k | E3: PV_k
A4: 1 | B4: 2.675 | C4: =B4/(1+$C$1)^A4 -> 2.5837996 | D4: 0.054388 | E4: =B4/(1+D4/2+$E$1)^A4 -> 2.5758708
A5: 2 | B5: 2.675 | C5: =B5/(1+$C$1)^A5 -> 2.4957085 | D5: 0.056791 | E5: =B5/(1+D5/2+$E$1)^A5 -> 2.4746854
A6: 3 | B6: 2.675 | C6: =B6/(1+$C$1)^A6 -> 2.4106207 | D6: 0.060158 | E6: =B6/(1+D6/2+$E$1)^A6 -> 2.3687004
A7: 4 | B7: 2.675 | C7: =B7/(1+$C$1)^A7 -> 2.3284339 | D7: 0.054117 | E7: =B7/(1+D7/2+$E$1)^A7 -> 2.3011854
A8: 5 | B8: 2.675 | C8: =B8/(1+$C$1)^A8 -> 2.2490492 | D8: 0.050885 | E8: =B8/(1+D8/2+$E$1)^A8 -> 2.2335244
A9: 6 | B9: 102.675 | C9: =B9/(1+$C$1)^A9 -> 83.3825 | D9: 0.047545 | E9: =B9/(1+D9/2+$E$1)^A9 -> 83.496034
A11: SUM | C11: =SUM(C4:C9) -> 95.450112 | E11: =SUM(E4:E9) -> 95.45

Sheet Case 3 - Bootstrap
A1: Zero-coupon curve bootstrapped from the observed Treasury securities
A3: Tenor (yrs) | B3: Coupon rate | C3: Price | D3: d_t | E3: z_t
A4: 0.5 | B4: 0.0375 | C4: 99.177975 | D4: =C4/(100+100*B4/2) -> 0.97352613 | E4: =2*(D4^(-1/(A4*2))-1) -> 0.05438758
A5: 1 | B5: 0.0505 | C5: 99.399571 | D5: =(C5-(100*B5/2)*SUM($D$4:D4))/(100+100*B5/2) -> 0.94553931 | E5: =2*(D5^(-1/(A5*2))-1) -> 0.056791182
A6: 1.5 | B6: 0.0639 | C6: 100.54778 | D6: =(C6-(100*B6/2)*SUM($D$4:D5))/(100+100*B6/2) -> 0.91493159 | E6: =2*(D6^(-1/(A6*2))-1) -> 0.060157644
A7: 2 | B7: 0.0244 | C7: 94.424926 | D7: =(C7-(100*B7/2)*SUM($D$4:D6))/(100+100*B7/2) -> 0.89871023 | E7: =2*(D7^(-1/(A7*2))-1) -> 0.054116514
A8: 2.5 | B8: 0.073 | C8: 105.0383 | D8: =(C8-(100*B8/2)*SUM($D$4:D7))/(100+100*B8/2) -> 0.88194813 | E8: =2*(D8^(-1/(A8*2))-1) -> 0.05088537
A9: 3 | B9: 0.0647 | C9: 104.58992 | D9: =(C9-(100*B9/2)*SUM($D$4:D8))/(100+100*B9/2) -> 0.86851848 | E9: =2*(D9^(-1/(A9*2))-1) -> 0.047545142

Sheet Case 3 - Q2 Q3
A1: Case 3 Part 2 - Pure expectations: 5% coupon, 2.5-year note, six months from now
A3: P_0 = PV today of the note cash flows | B3: =2.5*('Case 3 - Bootstrap'!D5+'Case 3 - Bootstrap'!D6+'Case 3 - Bootstrap'!D7+'Case 3 - Bootstrap'!D8)+102.5*'Case 3 - Bootstrap'!D9 -> 98.125967
A4: P_0.5 = P_0 / d(0.5) | B4: =B3/'Case 3 - Bootstrap'!D4 -> 100.79438
A5: Semi-annual yield r | B5: =RATE(5,2.5,-B4,100) -> 0.02329848
A6: YTM = 2 x r | B6: =2*B5 -> 0.04659696
A8: Case 3 Part 3 - 6% coupon, 3-year corporate bond, z-spread = 150 bps
A9: k | B9: CF_k | C9: z_k | D9: rate = z_k/2 + 0.75% | E9: PV_k
A10: 1 | B10: 3 | C10: ='Case 3 - Bootstrap'!E4 -> 0.05438758 | D10: =C10/2+0.0075 -> 0.03469379 | E10: =B10/(1+D10)^A10 -> 2.8994085
A11: 2 | B11: 3 | C11: ='Case 3 - Bootstrap'!E5 -> 0.056791182 | D11: =C11/2+0.0075 -> 0.035895591 | E11: =B11/(1+D11)^A11 -> 2.7956918
A12: 3 | B12: 3 | C12: ='Case 3 - Bootstrap'!E6 -> 0.060157644 | D12: =C12/2+0.0075 -> 0.037578822 | E12: =B12/(1+D12)^A12 -> 2.6857028
A13: 4 | B13: 3 | C13: ='Case 3 - Bootstrap'!E7 -> 0.054116514 | D13: =C13/2+0.0075 -> 0.034558257 | E13: =B13/(1+D13)^A13 -> 2.6187947
A14: 5 | B14: 3 | C14: ='Case 3 - Bootstrap'!E8 -> 0.05088537 | D14: =C14/2+0.0075 -> 0.032942685 | E14: =B14/(1+D14)^A14 -> 2.5511743
A15: 6 | B15: 103 | C15: ='Case 3 - Bootstrap'!E9 -> 0.047545142 | D15: =C15/2+0.0075 -> 0.031272571 | E15: =B15/(1+D15)^A15 -> 85.62418
A16: Price | B16: =SUM(E10:E15) -> 99.174952

Sheet Case 1 - Bond Price
A1: Case 1 - Heavy Equipment Bond (settlement 2026-07-03)
A3: Inputs
A4: Annual coupon | B4: 0.09
A5: Coupon frequency | B5: 2
A6: Annual YTM | B6: 0.076
A7: Par | B7: 100
A8: N (periods remaining) | B8: 13
A9: f (fraction of period) | B9: =3/180 -> 0.016666667
A11: Calculations
A12: Semi-annual coupon rate c | B12: =B4/B5 -> 0.045
A13: Semi-annual yield i | B13: =B6/B5 -> 0.038
A14: A = (1-(1+i)^(-N))/i | B14: =(1-(1+B13)^(-B8))/B13 -> 10.110723
A15: Full price FP | B15: =(1+B13)^B9*(B7+B7*(B12-B13)*B14) -> 107.14409
A16: Accrued interest AI = f*Par*c | B16: =B9*B7*B12 -> 0.075
A17: Clean (quoted) price | B17: =B15-B16 -> 107.06909
A19: Rock Bond - monthly 8.6% converted to semi-annual bond-equivalent
A20: APR (monthly) | B20: 0.086
A21: APR_2 = 2*((1+APR_12/12)^12)^(1/2) - 2 | B21: =2*((1+B20/12)^12)^0.5-2 -> 0.087555636
